odoo10_addon_report_qr-10.0.1.0.0.99.dev3-py3.8-nspkg.pth
odoo/addons/report_qr/README.rst
odoo/addons/report_qr/__init__.py
odoo/addons/report_qr/__manifest__.py
odoo/addons/report_qr/controllers/__init__.py
odoo/addons/report_qr/controllers/qr.py
odoo/addons/report_qr/i18n/report_qr.pot
odoo/addons/report_qr/models/__init__.py
odoo/addons/report_qr/models/report.py
odoo/addons/report_qr/readme/CONTRIBUTORS.rst
odoo/addons/report_qr/readme/DESCRIPTION.rst
odoo/addons/report_qr/readme/USAGE.rst
odoo/addons/report_qr/static/description/icon.png
odoo/addons/report_qr/static/description/index.html
odoo/addons/report_qr/static/description/new_qr.png
odoo/addons/report_qr/static/description/old_qr.png
odoo/addons/report_qr/tests/__init__.py
odoo/addons/report_qr/tests/test_report_qr.py
odoo10_addon_report_qr-10.0.1.0.0.99.dev3.dist-info/METADATA
odoo10_addon_report_qr-10.0.1.0.0.99.dev3.dist-info/WHEEL
odoo10_addon_report_qr-10.0.1.0.0.99.dev3.dist-info/namespace_packages.txt
odoo10_addon_report_qr-10.0.1.0.0.99.dev3.dist-info/top_level.txt
odoo10_addon_report_qr-10.0.1.0.0.99.dev3.dist-info/RECORD
